dynaparse/__init__.py
dynaparse/console.py
dynaparse/dynamic_configuration.py
dynaparse/parameters/__init__.py
dynaparse/parameters/base_parameter.py
dynaparse/parameters/boolean_parameter.py
dynaparse/parameters/categorical_parameter.py
dynaparse/parameters/float_parameter.py
dynaparse/parameters/int_parameter.py
dynaparse/parameters/list_parameter.py
dynaparse/parameters/string_parameter.py
dynaparse/parsers/__init__.py
dynaparse/parsers/class_model_parser.py
dynaparse/parsers/configuration_file_parser.py
dynaparse/parsers/dynamic_argument_parser.py
dynaparse/parsers/yaml_parser.py
dynaparse/util/__init__.py
dynaparse/util/schema_builder.py
tests/__init__.py
tests/test_dynamic_argument_parser.py
dynaparse-0.1a2.dist-info/LICENSE
dynaparse-0.1a2.dist-info/METADATA
dynaparse-0.1a2.dist-info/WHEEL
dynaparse-0.1a2.dist-info/entry_points.txt
dynaparse-0.1a2.dist-info/top_level.txt
dynaparse-0.1a2.dist-info/RECORD
