Metadata-Version: 2.1
Name: dynaparse
Version: 0.1a2
Summary: Library enabling dynamic configuration of scripts, especially for machine learning applications
Home-page: https://github.com/kungfuai/dynaparse
Author: KUNGFU.AI
Author-email: michael@kungfu.ai
License: UNKNOWN
Platform: UNKNOWN
Classifier: Development Status :: 3 - Alpha
Classifier: Intended Audience :: Developers
Classifier: Topic :: Software Development :: Libraries
Classifier: License :: OSI Approved :: MIT License
Classifier: Programming Language :: Python :: 3.6
Classifier: Programming Language :: Python :: 3.7
Classifier: Programming Language :: Python :: 3.8
Requires-Dist: typeguard (==2.10.0)
Requires-Dist: numpy (==1.19.2)
Requires-Dist: pydantic (==1.8)
Requires-Dist: pyyaml (==5.3.1)
